{
  "name": "rebekah4202",
  "dots": [
    {
      "x": 213.671875,
      "y": 229,
      "type": "2"
    },
    {
      "x": 259.671875,
      "y": 251,
      "type": "2"
    },
    {
      "x": 275.671875,
      "y": 286,
      "type": "2"
    },
    {
      "x": 269.671875,
      "y": 367,
      "type": "2"
    },
    {
      "x": 357.671875,
      "y": 379,
      "type": "2"
    },
    {
      "x": 347.671875,
      "y": 333,
      "type": "2"
    },
    {
      "x": 301.671875,
      "y": 200,
      "type": "2"
    },
    {
      "x": 272.671875,
      "y": 173,
      "type": "2"
    },
    {
      "x": 233.671875,
      "y": 173,
      "type": "2"
    },
    {
      "x": 198.671875,
      "y": 173,
      "type": "2"
    },
    {
      "x": 137.671875,
      "y": 227,
      "type": "4"
    },
    {
      "x": 131.671875,
      "y": 190,
      "type": "4"
    },
    {
      "x": 200.671875,
      "y": 140,
      "type": "1"
    },
    {
      "x": 144.671875,
      "y": 125,
      "type": "1"
    },
    {
      "x": 193.671875,
      "y": 121,
      "type": "1"
    },
    {
      "x": 242.671875,
      "y": 135,
      "type": "1"
    },
    {
      "x": 206.671875,
      "y": 269,
      "type": "1"
    },
    {
      "x": 237.671875,
      "y": 314,
      "type": "1"
    },
    {
      "x": 383.671875,
      "y": 320,
      "type": "1"
    },
    {
      "x": 171.671875,
      "y": 279,
      "type": "3"
    },
    {
      "x": 312.671875,
      "y": 246,
      "type": "3"
    },
    {
      "x": 317.671875,
      "y": 327,
      "type": "3"
    },
    {
      "x": 183.671875,
      "y": 321,
      "type": "2"
    },
    {
      "x": 146.671875,
      "y": 312,
      "type": "2"
    },
    {
      "x": 296.671875,
      "y": 154,
      "type": "2"
    },
    {
      "x": 338.671875,
      "y": 136,
      "type": "2"
    },
    {
      "x": 208.671875,
      "y": 363,
      "type": "2"
    },
    {
      "x": 361.671875,
      "y": 295,
      "type": "2"
    },
    {
      "x": 301.671875,
      "y": 367,
      "type": "2"
    }
  ],
  "ip": "20.0.0.6",
  "serverUTCDate": "2020-10-22T17:13:07.642993",
  "clientDate": "",
  "userAgent": {
    "browser": "Mozilla/5.0 (Windows NT 10.0; Win64; x64) AppleWebKit/537.36 (KHTML, like Gecko) Chrome/86.0.4240.75 Safari/537.36",
    "version": null,
    "language": "C.UTF-8"
  }
}