{
  "name": "rahmanh",
  "dots": [
    {
      "x": 272.671875,
      "y": 365,
      "type": "1"
    },
    {
      "x": 237.671875,
      "y": 375,
      "type": "1"
    },
    {
      "x": 308.671875,
      "y": 298,
      "type": "1"
    },
    {
      "x": 289.671875,
      "y": 223,
      "type": "1"
    },
    {
      "x": 371.671875,
      "y": 179,
      "type": "1"
    },
    {
      "x": 347.671875,
      "y": 286,
      "type": "1"
    },
    {
      "x": 371.671875,
      "y": 320,
      "type": "1"
    },
    {
      "x": 266.671875,
      "y": 318,
      "type": "1"
    }
  ],
  "ip": "20.0.0.6",
  "serverUTCDate": "2020-10-22T09:56:32.069719",
  "clientDate": "",
  "userAgent": {
    "browser": "Mozilla/5.0 (Windows NT 10.0; Win64; x64) AppleWebKit/537.36 (KHTML, like Gecko) Chrome/86.0.4240.80 Safari/537.36 Edg/86.0.622.48",
    "version": null,
    "language": "C.UTF-8"
  }
}