{
  "name": "Crystal",
  "dots": [
    {
      "x": 122.671875,
      "y": 286,
      "type": "1"
    },
    {
      "x": 371.671875,
      "y": 122,
      "type": "1"
    },
    {
      "x": 210.671875,
      "y": 371,
      "type": "1"
    },
    {
      "x": 221.671875,
      "y": 279,
      "type": "1"
    }
  ],
  "ip": "20.0.0.6",
  "serverUTCDate": "2020-10-27T19:42:23.925533",
  "clientDate": "",
  "userAgent": {
    "browser": "Mozilla/5.0 (Windows NT 10.0; Win64; x64) AppleWebKit/537.36 (KHTML, like Gecko) Chrome/86.0.4240.111 Safari/537.36",
    "version": null,
    "language": "C.UTF-8"
  }
}