{
  "name": "6mdperamunugamage@ash.bucks.sch.uk",
  "dots": [
    {
      "x": 159.5,
      "y": 166,
      "type": "1"
    },
    {
      "x": 139.5,
      "y": 306,
      "type": "1"
    },
    {
      "x": 226.5,
      "y": 275,
      "type": "1"
    },
    {
      "x": 210.5,
      "y": 366,
      "type": "1"
    }
  ],
  "ip": "20.0.0.6",
  "serverUTCDate": "2020-10-21T18:17:22.314559",
  "clientDate": "",
  "userAgent": {
    "browser": "Mozilla/5.0 (X11; CrOS x86_64 13310.93.0) AppleWebKit/537.36 (KHTML, like Gecko) Chrome/85.0.4183.133 Safari/537.36",
    "version": null,
    "language": "C.UTF-8"
  }
}