{
  "name": "ProfessorX",
  "dots": [
    {
      "x": 169.66668701171875,
      "y": 172.88333129882812,
      "type": "1"
    },
    {
      "x": 289.66668701171875,
      "y": 152.88333129882812,
      "type": "1"
    },
    {
      "x": 136.66668701171875,
      "y": 307.8833312988281,
      "type": "2"
    },
    {
      "x": 176.66668701171875,
      "y": 309.8833312988281,
      "type": "2"
    },
    {
      "x": 162.66668701171875,
      "y": 341.8833312988281,
      "type": "2"
    }
  ],
  "ip": "20.0.0.6",
  "serverUTCDate": "2020-11-11T17:33:01.553753",
  "clientDate": "",
  "userAgent": {
    "browser": "Mozilla/5.0 (Macintosh; Intel Mac OS X 10.15; rv:81.0) Gecko/20100101 Firefox/81.0",
    "version": null,
    "language": "C.UTF-8"
  }
}