{
  "name": "Nyne",
  "dots": [
    {
      "x": 271.814453125,
      "y": 217.544921875,
      "type": "1"
    },
    {
      "x": 214.814453125,
      "y": 203.544921875,
      "type": "1"
    },
    {
      "x": 379.814453125,
      "y": 343.544921875,
      "type": "1"
    },
    {
      "x": 377.814453125,
      "y": 167.544921875,
      "type": "1"
    },
    {
      "x": 326.814453125,
      "y": 173.544921875,
      "type": "2"
    },
    {
      "x": 309.814453125,
      "y": 154.544921875,
      "type": "2"
    },
    {
      "x": 291.814453125,
      "y": 142.544921875,
      "type": "2"
    },
    {
      "x": 250.814453125,
      "y": 158.544921875,
      "type": "2"
    },
    {
      "x": 251.814453125,
      "y": 191.544921875,
      "type": "2"
    },
    {
      "x": 314.814453125,
      "y": 224.544921875,
      "type": "2"
    },
    {
      "x": 314.814453125,
      "y": 279.544921875,
      "type": "2"
    },
    {
      "x": 338.814453125,
      "y": 313.544921875,
      "type": "2"
    },
    {
      "x": 352.814453125,
      "y": 334.544921875,
      "type": "2"
    },
    {
      "x": 381.814453125,
      "y": 261.544921875,
      "type": "2"
    },
    {
      "x": 213.814453125,
      "y": 274.544921875,
      "type": "2"
    },
    {
      "x": 143.814453125,
      "y": 312.544921875,
      "type": "2"
    },
    {
      "x": 135.814453125,
      "y": 340.544921875,
      "type": "2"
    },
    {
      "x": 145.814453125,
      "y": 190.544921875,
      "type": "2"
    },
    {
      "x": 143.814453125,
      "y": 160.544921875,
      "type": "2"
    }
  ],
  "ip": "20.0.0.6",
  "serverUTCDate": "2020-10-21T17:16:11.875909",
  "clientDate": "",
  "userAgent": {
    "browser": "Mozilla/5.0 (X11; CrOS x86_64 12871.91.0) AppleWebKit/537.36 (KHTML, like Gecko) Chrome/81.0.4044.127 Safari/537.36",
    "version": null,
    "language": "C.UTF-8"
  }
}