{
  "name": "ShaziaA",
  "dots": [
    {
      "x": 365.5104064941406,
      "y": 237.3333282470703,
      "type": "1"
    },
    {
      "x": 351.5104064941406,
      "y": 231.3333282470703,
      "type": "1"
    },
    {
      "x": 145.51040649414062,
      "y": 350.3333282470703,
      "type": "1"
    },
    {
      "x": 267.5104064941406,
      "y": 330.3333282470703,
      "type": "1"
    },
    {
      "x": 263.5104064941406,
      "y": 307.3333282470703,
      "type": "1"
    },
    {
      "x": 294.5104064941406,
      "y": 310.3333282470703,
      "type": "1"
    },
    {
      "x": 236.51040649414062,
      "y": 261.3333282470703,
      "type": "1"
    },
    {
      "x": 229.51040649414062,
      "y": 276.3333282470703,
      "type": "1"
    },
    {
      "x": 327.5104064941406,
      "y": 354.3333282470703,
      "type": "1"
    }
  ],
  "ip": "20.0.0.6",
  "serverUTCDate": "2020-10-22T14:34:16.612727",
  "clientDate": "",
  "userAgent": {
    "browser": "Mozilla/5.0 (Windows NT 10.0; Win64; x64) AppleWebKit/537.36 (KHTML, like Gecko) Chrome/86.0.4240.75 Safari/537.36",
    "version": null,
    "language": "C.UTF-8"
  }
}