{
  "name": "Ams",
  "dots": [
    {
      "x": 305.17498779296875,
      "y": 191,
      "type": "1"
    },
    {
      "x": 281.17498779296875,
      "y": 196,
      "type": "1"
    },
    {
      "x": 199.17498779296875,
      "y": 146,
      "type": "1"
    },
    {
      "x": 152.17498779296875,
      "y": 145,
      "type": "1"
    },
    {
      "x": 131.17498779296875,
      "y": 153,
      "type": "1"
    },
    {
      "x": 135.17498779296875,
      "y": 240,
      "type": "1"
    },
    {
      "x": 179.17498779296875,
      "y": 285,
      "type": "1"
    },
    {
      "x": 211.17498779296875,
      "y": 314,
      "type": "1"
    },
    {
      "x": 283.17498779296875,
      "y": 283,
      "type": "1"
    },
    {
      "x": 312.17498779296875,
      "y": 287,
      "type": "1"
    },
    {
      "x": 295.17498779296875,
      "y": 304,
      "type": "1"
    },
    {
      "x": 350.17498779296875,
      "y": 277,
      "type": "1"
    },
    {
      "x": 338.17498779296875,
      "y": 349,
      "type": "1"
    },
    {
      "x": 339.17498779296875,
      "y": 361,
      "type": "1"
    },
    {
      "x": 313.17498779296875,
      "y": 361,
      "type": "1"
    },
    {
      "x": 229.17498779296875,
      "y": 356,
      "type": "1"
    },
    {
      "x": 202.17498779296875,
      "y": 379,
      "type": "1"
    },
    {
      "x": 383.17498779296875,
      "y": 373,
      "type": "1"
    },
    {
      "x": 370.17498779296875,
      "y": 296,
      "type": "1"
    },
    {
      "x": 383.17498779296875,
      "y": 258,
      "type": "1"
    },
    {
      "x": 347.17498779296875,
      "y": 199,
      "type": "1"
    },
    {
      "x": 286.17498779296875,
      "y": 255,
      "type": "1"
    }
  ],
  "ip": "20.0.0.6",
  "serverUTCDate": "2020-11-03T20:47:01.264410",
  "clientDate": "",
  "userAgent": {
    "browser": "Mozilla/5.0 (X11; CrOS x86_64 13421.73.0) AppleWebKit/537.36 (KHTML, like Gecko) Chrome/86.0.4240.112 Safari/537.36",
    "version": null,
    "language": "C.UTF-8"
  }
}