{
  "name": "brock.liv",
  "dots": [
    {
      "x": 259.671875,
      "y": 235,
      "type": "1"
    },
    {
      "x": 274.671875,
      "y": 295,
      "type": "1"
    },
    {
      "x": 364.671875,
      "y": 183,
      "type": "1"
    },
    {
      "x": 346.671875,
      "y": 246,
      "type": "1"
    },
    {
      "x": 372.671875,
      "y": 233,
      "type": "1"
    },
    {
      "x": 378.671875,
      "y": 276,
      "type": "1"
    },
    {
      "x": 233.671875,
      "y": 174,
      "type": "1"
    },
    {
      "x": 194.671875,
      "y": 159,
      "type": "2"
    },
    {
      "x": 201.671875,
      "y": 266,
      "type": "2"
    },
    {
      "x": 255.671875,
      "y": 363,
      "type": "2"
    },
    {
      "x": 312.671875,
      "y": 325,
      "type": "2"
    },
    {
      "x": 352.671875,
      "y": 309,
      "type": "2"
    },
    {
      "x": 316.671875,
      "y": 282,
      "type": "2"
    },
    {
      "x": 264.671875,
      "y": 185,
      "type": "2"
    },
    {
      "x": 296.671875,
      "y": 221,
      "type": "2"
    },
    {
      "x": 246.671875,
      "y": 141,
      "type": "2"
    }
  ],
  "ip": "20.0.0.6",
  "serverUTCDate": "2020-11-06T13:03:17.677036",
  "clientDate": "",
  "userAgent": {
    "browser": "Mozilla/5.0 (Windows NT 10.0; Win64; x64) AppleWebKit/537.36 (KHTML, like Gecko) Chrome/85.0.4183.121 Safari/537.36",
    "version": null,
    "language": "C.UTF-8"
  }
}