{
  "name": "CarysWinstanley",
  "dots": [
    {
      "x": 324.171875,
      "y": 278,
      "type": "1"
    },
    {
      "x": 355.171875,
      "y": 240,
      "type": "1"
    },
    {
      "x": 254.171875,
      "y": 158,
      "type": "1"
    },
    {
      "x": 166.171875,
      "y": 247,
      "type": "1"
    },
    {
      "x": 245.171875,
      "y": 315,
      "type": "1"
    },
    {
      "x": 245.171875,
      "y": 262,
      "type": "3"
    },
    {
      "x": 191.171875,
      "y": 255,
      "type": "3"
    },
    {
      "x": 191.171875,
      "y": 335,
      "type": "3"
    },
    {
      "x": 137.171875,
      "y": 369,
      "type": "3"
    },
    {
      "x": 186.171875,
      "y": 175,
      "type": "2"
    },
    {
      "x": 221.171875,
      "y": 181,
      "type": "2"
    },
    {
      "x": 269.171875,
      "y": 191,
      "type": "2"
    },
    {
      "x": 325.171875,
      "y": 189,
      "type": "2"
    },
    {
      "x": 284.171875,
      "y": 305,
      "type": "2"
    },
    {
      "x": 304.171875,
      "y": 346,
      "type": "2"
    },
    {
      "x": 359.171875,
      "y": 349,
      "type": "2"
    },
    {
      "x": 335.171875,
      "y": 311,
      "type": "2"
    },
    {
      "x": 145.171875,
      "y": 326,
      "type": "2"
    },
    {
      "x": 141.171875,
      "y": 258,
      "type": "2"
    }
  ],
  "ip": "20.0.0.6",
  "serverUTCDate": "2020-10-20T17:33:10.296033",
  "clientDate": "",
  "userAgent": {
    "browser": "Mozilla/5.0 (Macintosh; Intel Mac OS X 10_15_3) AppleWebKit/605.1.15 (KHTML, like Gecko) Version/13.0.5 Safari/605.1.15",
    "version": null,
    "language": "C.UTF-8"
  }
}