{
  "name": "Ams",
  "dots": [
    {
      "x": 160,
      "y": 372,
      "type": "1"
    },
    {
      "x": 170,
      "y": 376,
      "type": "1"
    },
    {
      "x": 184,
      "y": 343,
      "type": "1"
    },
    {
      "x": 129,
      "y": 313,
      "type": "1"
    },
    {
      "x": 152,
      "y": 247,
      "type": "1"
    },
    {
      "x": 158,
      "y": 227,
      "type": "1"
    },
    {
      "x": 184,
      "y": 254,
      "type": "1"
    },
    {
      "x": 201,
      "y": 248,
      "type": "1"
    },
    {
      "x": 245,
      "y": 239,
      "type": "1"
    },
    {
      "x": 286,
      "y": 289,
      "type": "1"
    },
    {
      "x": 300,
      "y": 269,
      "type": "1"
    },
    {
      "x": 314,
      "y": 280,
      "type": "1"
    },
    {
      "x": 376,
      "y": 352,
      "type": "1"
    },
    {
      "x": 382,
      "y": 362,
      "type": "1"
    },
    {
      "x": 290,
      "y": 132,
      "type": "1"
    },
    {
      "x": 336,
      "y": 127,
      "type": "1"
    },
    {
      "x": 195,
      "y": 148,
      "type": "1"
    }
  ],
  "ip": "20.0.0.6",
  "serverUTCDate": "2020-11-15T19:44:29.239889",
  "clientDate": "",
  "userAgent": {
    "browser": "Mozilla/5.0 (iPhone; CPU iPhone OS 14_2 like Mac OS X) AppleWebKit/605.1.15 (KHTML, like Gecko) Version/14.0.1 Mobile/15E148 Safari/604.1",
    "version": null,
    "language": "C.UTF-8"
  }
}