{
  "name": "AmalWatk",
  "dots": [
    {
      "x": 158.51040649414062,
      "y": 163.3333282470703,
      "type": "1"
    },
    {
      "x": 305.5104064941406,
      "y": 278.3333282470703,
      "type": "1"
    },
    {
      "x": 239.51040649414062,
      "y": 305.3333282470703,
      "type": "1"
    },
    {
      "x": 289.5104064941406,
      "y": 309.3333282470703,
      "type": "1"
    },
    {
      "x": 337.5104064941406,
      "y": 324.3333282470703,
      "type": "1"
    },
    {
      "x": 374.5104064941406,
      "y": 328.3333282470703,
      "type": "1"
    },
    {
      "x": 367.5104064941406,
      "y": 374.3333282470703,
      "type": "1"
    },
    {
      "x": 335.5104064941406,
      "y": 177.3333282470703,
      "type": "3"
    },
    {
      "x": 248.51040649414062,
      "y": 146.3333282470703,
      "type": "2"
    },
    {
      "x": 217.51040649414062,
      "y": 138.3333282470703,
      "type": "2"
    },
    {
      "x": 181.51040649414062,
      "y": 132.3333282470703,
      "type": "2"
    },
    {
      "x": 287.5104064941406,
      "y": 146.3333282470703,
      "type": "2"
    },
    {
      "x": 313.5104064941406,
      "y": 144.3333282470703,
      "type": "2"
    },
    {
      "x": 272.5104064941406,
      "y": 178.3333282470703,
      "type": "2"
    },
    {
      "x": 203.51040649414062,
      "y": 229.3333282470703,
      "type": "2"
    },
    {
      "x": 251.51040649414062,
      "y": 236.3333282470703,
      "type": "2"
    },
    {
      "x": 357.5104064941406,
      "y": 213.3333282470703,
      "type": "2"
    },
    {
      "x": 307.5104064941406,
      "y": 208.3333282470703,
      "type": "2"
    },
    {
      "x": 327.5104064941406,
      "y": 240.3333282470703,
      "type": "2"
    },
    {
      "x": 294.5104064941406,
      "y": 238.3333282470703,
      "type": "2"
    }
  ],
  "ip": "20.0.0.6",
  "serverUTCDate": "2020-11-02T18:29:18.920556",
  "clientDate": "",
  "userAgent": {
    "browser": "Mozilla/5.0 (Windows NT 10.0; Win64; x64) AppleWebKit/537.36 (KHTML, like Gecko) Chrome/86.0.4240.111 Safari/537.36",
    "version": null,
    "language": "C.UTF-8"
  }
}