{
  "name": "oyaoyaoya3",
  "dots": [
    {
      "x": 168.671875,
      "y": 139,
      "type": "1"
    },
    {
      "x": 375.671875,
      "y": 188,
      "type": "1"
    },
    {
      "x": 149.671875,
      "y": 321,
      "type": "3"
    },
    {
      "x": 239.671875,
      "y": 160,
      "type": "2"
    },
    {
      "x": 209.671875,
      "y": 175,
      "type": "1"
    },
    {
      "x": 344.671875,
      "y": 249,
      "type": "2"
    },
    {
      "x": 290.671875,
      "y": 209,
      "type": "2"
    },
    {
      "x": 194.671875,
      "y": 323,
      "type": "2"
    },
    {
      "x": 152.671875,
      "y": 281,
      "type": "2"
    },
    {
      "x": 240.671875,
      "y": 230,
      "type": "2"
    },
    {
      "x": 267.671875,
      "y": 138,
      "type": "2"
    },
    {
      "x": 151.671875,
      "y": 362,
      "type": "2"
    },
    {
      "x": 376.671875,
      "y": 345,
      "type": "2"
    },
    {
      "x": 338.671875,
      "y": 166,
      "type": "2"
    },
    {
      "x": 137.671875,
      "y": 197,
      "type": "4"
    },
    {
      "x": 159.671875,
      "y": 231,
      "type": "4"
    },
    {
      "x": 144.671875,
      "y": 241,
      "type": "4"
    },
    {
      "x": 327.671875,
      "y": 337,
      "type": "4"
    },
    {
      "x": 242.671875,
      "y": 347,
      "type": "4"
    },
    {
      "x": 270.671875,
      "y": 339,
      "type": "4"
    },
    {
      "x": 254.671875,
      "y": 264,
      "type": "2"
    },
    {
      "x": 296.671875,
      "y": 242,
      "type": "2"
    }
  ],
  "ip": "20.0.0.6",
  "serverUTCDate": "2020-10-29T09:05:35.193578",
  "clientDate": "",
  "userAgent": {
    "browser": "Mozilla/5.0 (Windows NT 6.3; Win64; x64) AppleWebKit/537.36 (KHTML, like Gecko) Chrome/86.0.4240.111 Safari/537.36",
    "version": null,
    "language": "C.UTF-8"
  }
}