{
  "name": "rahmanh",
  "dots": [
    {
      "x": 133.671875,
      "y": 306,
      "type": "1"
    },
    {
      "x": 158.671875,
      "y": 156,
      "type": "1"
    },
    {
      "x": 223.671875,
      "y": 283,
      "type": "1"
    },
    {
      "x": 208.671875,
      "y": 372,
      "type": "1"
    }
  ],
  "ip": "20.0.0.6",
  "serverUTCDate": "2020-11-07T13:09:40.051576",
  "clientDate": "",
  "userAgent": {
    "browser": "Mozilla/5.0 (Windows NT 10.0; Win64; x64) AppleWebKit/537.36 (KHTML, like Gecko) Chrome/86.0.4240.111 Safari/537.36 Edg/86.0.622.58",
    "version": null,
    "language": "C.UTF-8"
  }
}