{
  "name": "AmalWatk",
  "dots": [
    {
      "x": 329.5104064941406,
      "y": 166.66666412353516,
      "type": "1"
    },
    {
      "x": 319.5104064941406,
      "y": 139.66666412353516,
      "type": "1"
    },
    {
      "x": 358.5104064941406,
      "y": 157.66666412353516,
      "type": "1"
    },
    {
      "x": 150.51040649414062,
      "y": 177.66666412353516,
      "type": "1"
    },
    {
      "x": 215.51040649414062,
      "y": 330.66666412353516,
      "type": "1"
    },
    {
      "x": 385.5104064941406,
      "y": 306.66666412353516,
      "type": "1"
    },
    {
      "x": 372.5104064941406,
      "y": 363.66666412353516,
      "type": "1"
    },
    {
      "x": 159.51040649414062,
      "y": 351.66666412353516,
      "type": "1"
    },
    {
      "x": 193.51040649414062,
      "y": 285.66666412353516,
      "type": "1"
    }
  ],
  "ip": "20.0.0.6",
  "serverUTCDate": "2020-11-02T17:08:36.667177",
  "clientDate": "",
  "userAgent": {
    "browser": "Mozilla/5.0 (Windows NT 10.0; Win64; x64) AppleWebKit/537.36 (KHTML, like Gecko) Chrome/86.0.4240.111 Safari/537.36",
    "version": null,
    "language": "C.UTF-8"
  }
}