{
  "name": "anjola_axox",
  "dots": [
    {
      "x": 266.171875,
      "y": 164,
      "type": "1"
    },
    {
      "x": 294.171875,
      "y": 156,
      "type": "1"
    },
    {
      "x": 314.171875,
      "y": 208,
      "type": "1"
    },
    {
      "x": 225.171875,
      "y": 364,
      "type": "1"
    },
    {
      "x": 336.171875,
      "y": 339,
      "type": "1"
    },
    {
      "x": 345.171875,
      "y": 163,
      "type": "1"
    },
    {
      "x": 257.171875,
      "y": 282,
      "type": "3"
    },
    {
      "x": 147.171875,
      "y": 271,
      "type": "3"
    },
    {
      "x": 224.171875,
      "y": 278,
      "type": "2"
    },
    {
      "x": 191.171875,
      "y": 290,
      "type": "2"
    },
    {
      "x": 160.171875,
      "y": 287,
      "type": "2"
    },
    {
      "x": 182.171875,
      "y": 257,
      "type": "2"
    },
    {
      "x": 276.171875,
      "y": 241,
      "type": "2"
    },
    {
      "x": 268.171875,
      "y": 210,
      "type": "2"
    },
    {
      "x": 292.171875,
      "y": 190,
      "type": "2"
    },
    {
      "x": 355.171875,
      "y": 136,
      "type": "2"
    },
    {
      "x": 378.171875,
      "y": 151,
      "type": "2"
    },
    {
      "x": 303.171875,
      "y": 367,
      "type": "2"
    },
    {
      "x": 209.171875,
      "y": 332,
      "type": "2"
    },
    {
      "x": 247.171875,
      "y": 320,
      "type": "2"
    },
    {
      "x": 373.171875,
      "y": 362,
      "type": "2"
    },
    {
      "x": 275.171875,
      "y": 135,
      "type": "2"
    },
    {
      "x": 379.171875,
      "y": 333,
      "type": "2"
    },
    {
      "x": 136.171875,
      "y": 136,
      "type": "2"
    }
  ],
  "ip": "20.0.0.6",
  "serverUTCDate": "2020-10-22T18:59:52.892153",
  "clientDate": "",
  "userAgent": {
    "browser": "Mozilla/5.0 (X11; CrOS x86_64 13310.93.0) AppleWebKit/537.36 (KHTML, like Gecko) Chrome/85.0.4183.133 Safari/537.36",
    "version": null,
    "language": "C.UTF-8"
  }
}