{
  "name": "Florence",
  "dots": [
    {
      "x": 212.17498779296875,
      "y": 382.3999938964844,
      "type": "1"
    },
    {
      "x": 245.17498779296875,
      "y": 279.3999938964844,
      "type": "1"
    },
    {
      "x": 301.17498779296875,
      "y": 275.3999938964844,
      "type": "1"
    },
    {
      "x": 355.17498779296875,
      "y": 179.39999389648438,
      "type": "1"
    },
    {
      "x": 354.17498779296875,
      "y": 134.39999389648438,
      "type": "1"
    },
    {
      "x": 384.17498779296875,
      "y": 147.39999389648438,
      "type": "1"
    },
    {
      "x": 154.17498779296875,
      "y": 375.3999938964844,
      "type": "1"
    }
  ],
  "ip": "20.0.0.6",
  "serverUTCDate": "2020-10-26T19:01:20.941245",
  "clientDate": "",
  "userAgent": {
    "browser": "Mozilla/5.0 (X11; CrOS x86_64 13310.93.0) AppleWebKit/537.36 (KHTML, like Gecko) Chrome/85.0.4183.133 Safari/537.36",
    "version": null,
    "language": "C.UTF-8"
  }
}