{
  "name": "Blaise2408",
  "dots": [
    {
      "x": 230.501953125,
      "y": 220.67578125,
      "type": "1"
    },
    {
      "x": 227.501953125,
      "y": 373.67578125,
      "type": "1"
    },
    {
      "x": 243.501953125,
      "y": 293.67578125,
      "type": "1"
    },
    {
      "x": 134.501953125,
      "y": 222.67578125,
      "type": "1"
    }
  ],
  "ip": "20.0.0.6",
  "serverUTCDate": "2020-10-21T16:46:56.280305",
  "clientDate": "",
  "userAgent": {
    "browser": "Mozilla/5.0 (X11; CrOS x86_64 13421.53.0) AppleWebKit/537.36 (KHTML, like Gecko) Chrome/86.0.4240.77 Safari/537.36",
    "version": null,
    "language": "C.UTF-8"
  }
}