{
  "name": "M_Yahie",
  "dots": [
    {
      "x": 308.671875,
      "y": 245,
      "type": "1"
    },
    {
      "x": 268.671875,
      "y": 199,
      "type": "1"
    },
    {
      "x": 210.671875,
      "y": 304,
      "type": "1"
    },
    {
      "x": 182.671875,
      "y": 276,
      "type": "2"
    },
    {
      "x": 307.671875,
      "y": 353,
      "type": "2"
    },
    {
      "x": 235.671875,
      "y": 154,
      "type": "2"
    },
    {
      "x": 231.671875,
      "y": 256,
      "type": "2"
    }
  ],
  "ip": "20.0.0.6",
  "serverUTCDate": "2020-10-28T16:15:31.091685",
  "clientDate": "",
  "userAgent": {
    "browser": "Mozilla/5.0 (X11; CrOS x86_64 13421.73.0) AppleWebKit/537.36 (KHTML, like Gecko) Chrome/86.0.4240.112 Safari/537.36",
    "version": null,
    "language": "C.UTF-8"
  }
}