{
  "name": "M_Yahie",
  "dots": [
    {
      "x": 201.171875,
      "y": 172,
      "type": "1"
    },
    {
      "x": 170.171875,
      "y": 224,
      "type": "1"
    },
    {
      "x": 165.171875,
      "y": 316,
      "type": "1"
    },
    {
      "x": 334.171875,
      "y": 271,
      "type": "1"
    },
    {
      "x": 271.171875,
      "y": 324,
      "type": "1"
    },
    {
      "x": 248.171875,
      "y": 252,
      "type": "1"
    },
    {
      "x": 312.171875,
      "y": 185,
      "type": "2"
    },
    {
      "x": 211.171875,
      "y": 362,
      "type": "2"
    },
    {
      "x": 319.171875,
      "y": 221,
      "type": "2"
    }
  ],
  "ip": "20.0.0.6",
  "serverUTCDate": "2020-10-28T16:07:12.898389",
  "clientDate": "",
  "userAgent": {
    "browser": "Mozilla/5.0 (X11; CrOS x86_64 13421.73.0) AppleWebKit/537.36 (KHTML, like Gecko) Chrome/86.0.4240.112 Safari/537.36",
    "version": null,
    "language": "C.UTF-8"
  }
}