{
  "name": "QuincyJnr",
  "dots": [
    {
      "x": 146.171875,
      "y": 181,
      "type": "1"
    },
    {
      "x": 144.171875,
      "y": 258,
      "type": "1"
    },
    {
      "x": 172.171875,
      "y": 272,
      "type": "1"
    },
    {
      "x": 308.171875,
      "y": 138,
      "type": "1"
    },
    {
      "x": 294.171875,
      "y": 240,
      "type": "1"
    },
    {
      "x": 359.171875,
      "y": 329,
      "type": "1"
    },
    {
      "x": 345.171875,
      "y": 286,
      "type": "1"
    },
    {
      "x": 368.171875,
      "y": 255,
      "type": "1"
    },
    {
      "x": 369.171875,
      "y": 291,
      "type": "1"
    },
    {
      "x": 217.171875,
      "y": 296,
      "type": "2"
    },
    {
      "x": 190.171875,
      "y": 251,
      "type": "2"
    },
    {
      "x": 180.171875,
      "y": 201,
      "type": "2"
    },
    {
      "x": 176.171875,
      "y": 185,
      "type": "2"
    },
    {
      "x": 200.171875,
      "y": 176,
      "type": "2"
    },
    {
      "x": 262.171875,
      "y": 167,
      "type": "2"
    },
    {
      "x": 339.171875,
      "y": 137,
      "type": "2"
    },
    {
      "x": 265.171875,
      "y": 278,
      "type": "2"
    },
    {
      "x": 208.171875,
      "y": 339,
      "type": "2"
    },
    {
      "x": 239.171875,
      "y": 372,
      "type": "2"
    },
    {
      "x": 277.171875,
      "y": 356,
      "type": "2"
    },
    {
      "x": 339.171875,
      "y": 368,
      "type": "2"
    }
  ],
  "ip": "20.0.0.6",
  "serverUTCDate": "2020-11-08T13:35:21.062971",
  "clientDate": "",
  "userAgent": {
    "browser": "Mozilla/5.0 (Macintosh; Intel Mac OS X 10_15_6) AppleWebKit/605.1.15 (KHTML, like Gecko) Version/14.0 Safari/605.1.15",
    "version": null,
    "language": "C.UTF-8"
  }
}