{
  "name": "Mrollie",
  "dots": [
    {
      "x": 261.17706298828125,
      "y": 307.3333282470703,
      "type": "1"
    },
    {
      "x": 133.17706298828125,
      "y": 198.3333282470703,
      "type": "1"
    },
    {
      "x": 328.17706298828125,
      "y": 374.3333282470703,
      "type": "1"
    },
    {
      "x": 358.17706298828125,
      "y": 308.3333282470703,
      "type": "1"
    },
    {
      "x": 275.17706298828125,
      "y": 150.3333282470703,
      "type": "1"
    }
  ],
  "ip": "20.0.0.6",
  "serverUTCDate": "2020-11-09T14:19:13.528643",
  "clientDate": "",
  "userAgent": {
    "browser": "Mozilla/5.0 (Windows NT 10.0; Win64; x64) AppleWebKit/537.36 (KHTML, like Gecko) Chrome/86.0.4240.183 Safari/537.36",
    "version": null,
    "language": "C.UTF-8"
  }
}