{
  "name": "Mrollie",
  "dots": [
    {
      "x": 290.17706298828125,
      "y": 199.3333282470703,
      "type": "1"
    },
    {
      "x": 267.17706298828125,
      "y": 234.3333282470703,
      "type": "1"
    },
    {
      "x": 220.17706298828125,
      "y": 267.3333282470703,
      "type": "1"
    },
    {
      "x": 287.17706298828125,
      "y": 342.3333282470703,
      "type": "1"
    },
    {
      "x": 273.17706298828125,
      "y": 373.3333282470703,
      "type": "1"
    },
    {
      "x": 213.17706298828125,
      "y": 348.3333282470703,
      "type": "1"
    },
    {
      "x": 368.17706298828125,
      "y": 239.3333282470703,
      "type": "2"
    }
  ],
  "ip": "20.0.0.6",
  "serverUTCDate": "2020-11-09T14:23:46.635289",
  "clientDate": "",
  "userAgent": {
    "browser": "Mozilla/5.0 (Windows NT 10.0; Win64; x64) AppleWebKit/537.36 (KHTML, like Gecko) Chrome/86.0.4240.183 Safari/537.36",
    "version": null,
    "language": "C.UTF-8"
  }
}