{
  "name": "Florence",
  "dots": [
    {
      "x": 342.1710510253906,
      "y": 130.2105255126953,
      "type": "1"
    },
    {
      "x": 301.1710510253906,
      "y": 134.2105255126953,
      "type": "1"
    },
    {
      "x": 192.17105102539062,
      "y": 145.2105255126953,
      "type": "1"
    },
    {
      "x": 152.17105102539062,
      "y": 229.2105255126953,
      "type": "1"
    },
    {
      "x": 185.17105102539062,
      "y": 254.2105255126953,
      "type": "1"
    },
    {
      "x": 243.17105102539062,
      "y": 247.2105255126953,
      "type": "1"
    },
    {
      "x": 298.1710510253906,
      "y": 281.2105255126953,
      "type": "1"
    },
    {
      "x": 375.1710510253906,
      "y": 352.2105255126953,
      "type": "1"
    },
    {
      "x": 276.1710510253906,
      "y": 362.2105255126953,
      "type": "1"
    },
    {
      "x": 180.17105102539062,
      "y": 339.2105255126953,
      "type": "1"
    },
    {
      "x": 168.17105102539062,
      "y": 369.2105255126953,
      "type": "1"
    },
    {
      "x": 132.17105102539062,
      "y": 312.2105255126953,
      "type": "1"
    }
  ],
  "ip": "20.0.0.6",
  "serverUTCDate": "2020-10-27T17:09:59.656680",
  "clientDate": "",
  "userAgent": {
    "browser": "Mozilla/5.0 (X11; CrOS x86_64 13421.73.0) AppleWebKit/537.36 (KHTML, like Gecko) Chrome/86.0.4240.112 Safari/537.36",
    "version": null,
    "language": "C.UTF-8"
  }
}