{
  "name": "fluffy10",
  "dots": [
    {
      "x": 289.671875,
      "y": 210,
      "type": "1"
    },
    {
      "x": 214.671875,
      "y": 165,
      "type": "1"
    },
    {
      "x": 196.671875,
      "y": 211,
      "type": "1"
    },
    {
      "x": 215.671875,
      "y": 252,
      "type": "2"
    },
    {
      "x": 168.671875,
      "y": 241,
      "type": "2"
    },
    {
      "x": 272.671875,
      "y": 151,
      "type": "2"
    },
    {
      "x": 285.671875,
      "y": 270,
      "type": "2"
    }
  ],
  "ip": "20.0.0.6",
  "serverUTCDate": "2020-10-17T14:11:35.222206",
  "clientDate": "",
  "userAgent": {
    "browser": "Mozilla/5.0 (Windows NT 10.0; Win64; x64) AppleWebKit/537.36 (KHTML, like Gecko) Chrome/75.0.3770.142 Safari/537.36",
    "version": null,
    "language": "C.UTF-8"
  }
}