{
  "name": "Ams",
  "dots": [
    {
      "x": 250.17105102539062,
      "y": 144.4736785888672,
      "type": "1"
    },
    {
      "x": 198.17105102539062,
      "y": 127.47367858886719,
      "type": "1"
    },
    {
      "x": 245.17105102539062,
      "y": 341.4736785888672,
      "type": "1"
    },
    {
      "x": 209.17105102539062,
      "y": 384.4736785888672,
      "type": "1"
    },
    {
      "x": 138.17105102539062,
      "y": 372.4736785888672,
      "type": "1"
    },
    {
      "x": 126.17105102539062,
      "y": 342.4736785888672,
      "type": "1"
    },
    {
      "x": 153.17105102539062,
      "y": 389.4736785888672,
      "type": "1"
    }
  ],
  "ip": "20.0.0.6",
  "serverUTCDate": "2020-10-30T22:25:40.001214",
  "clientDate": "",
  "userAgent": {
    "browser": "Mozilla/5.0 (X11; CrOS x86_64 13421.73.0) AppleWebKit/537.36 (KHTML, like Gecko) Chrome/86.0.4240.112 Safari/537.36",
    "version": null,
    "language": "C.UTF-8"
  }
}