{
  "name": "ProfessorX",
  "dots": [
    {
      "x": 338.16668701171875,
      "y": 185.88333129882812,
      "type": "1"
    },
    {
      "x": 375.16668701171875,
      "y": 183.88333129882812,
      "type": "1"
    },
    {
      "x": 329.16668701171875,
      "y": 211.88333129882812,
      "type": "1"
    },
    {
      "x": 387.16668701171875,
      "y": 259.8833312988281,
      "type": "1"
    }
  ],
  "ip": "20.0.0.6",
  "serverUTCDate": "2020-11-07T14:02:48.586300",
  "clientDate": "",
  "userAgent": {
    "browser": "Mozilla/5.0 (Macintosh; Intel Mac OS X 10.15; rv:81.0) Gecko/20100101 Firefox/81.0",
    "version": null,
    "language": "C.UTF-8"
  }
}