{
  "name": "Nyne",
  "dots": [
    {
      "x": 244.814453125,
      "y": 305.169921875,
      "type": "1"
    },
    {
      "x": 288.814453125,
      "y": 308.169921875,
      "type": "1"
    },
    {
      "x": 307.814453125,
      "y": 272.169921875,
      "type": "1"
    },
    {
      "x": 332.814453125,
      "y": 319.169921875,
      "type": "1"
    },
    {
      "x": 377.814453125,
      "y": 323.169921875,
      "type": "1"
    },
    {
      "x": 295.814453125,
      "y": 385.169921875,
      "type": "1"
    },
    {
      "x": 368.814453125,
      "y": 378.169921875,
      "type": "1"
    },
    {
      "x": 335.814453125,
      "y": 180.169921875,
      "type": "1"
    },
    {
      "x": 167.814453125,
      "y": 161.169921875,
      "type": "1"
    },
    {
      "x": 242.814453125,
      "y": 377.169921875,
      "type": "3"
    },
    {
      "x": 308.814453125,
      "y": 338.169921875,
      "type": "3"
    },
    {
      "x": 196.814453125,
      "y": 225.169921875,
      "type": "2"
    },
    {
      "x": 249.814453125,
      "y": 243.169921875,
      "type": "2"
    },
    {
      "x": 281.814453125,
      "y": 174.169921875,
      "type": "2"
    },
    {
      "x": 291.814453125,
      "y": 149.169921875,
      "type": "2"
    },
    {
      "x": 311.814453125,
      "y": 150.169921875,
      "type": "2"
    },
    {
      "x": 254.814453125,
      "y": 149.169921875,
      "type": "2"
    },
    {
      "x": 215.814453125,
      "y": 136.169921875,
      "type": "2"
    },
    {
      "x": 183.814453125,
      "y": 136.169921875,
      "type": "2"
    },
    {
      "x": 238.814453125,
      "y": 193.169921875,
      "type": "2"
    },
    {
      "x": 165.814453125,
      "y": 211.169921875,
      "type": "2"
    },
    {
      "x": 165.814453125,
      "y": 269.169921875,
      "type": "2"
    },
    {
      "x": 183.814453125,
      "y": 319.169921875,
      "type": "2"
    },
    {
      "x": 195.814453125,
      "y": 354.169921875,
      "type": "2"
    },
    {
      "x": 280.814453125,
      "y": 347.169921875,
      "type": "2"
    },
    {
      "x": 335.814453125,
      "y": 360.169921875,
      "type": "2"
    },
    {
      "x": 350.814453125,
      "y": 344.169921875,
      "type": "2"
    },
    {
      "x": 322.814453125,
      "y": 215.169921875,
      "type": "2"
    },
    {
      "x": 328.814453125,
      "y": 240.169921875,
      "type": "2"
    },
    {
      "x": 354.814453125,
      "y": 220.169921875,
      "type": "2"
    },
    {
      "x": 367.814453125,
      "y": 253.169921875,
      "type": "2"
    },
    {
      "x": 290.814453125,
      "y": 244.169921875,
      "type": "2"
    },
    {
      "x": 268.814453125,
      "y": 223.169921875,
      "type": "2"
    },
    {
      "x": 130.814453125,
      "y": 360.169921875,
      "type": "2"
    }
  ],
  "ip": "20.0.0.6",
  "serverUTCDate": "2020-10-21T17:40:39.501400",
  "clientDate": "",
  "userAgent": {
    "browser": "Mozilla/5.0 (X11; CrOS x86_64 12871.91.0) AppleWebKit/537.36 (KHTML, like Gecko) Chrome/81.0.4044.127 Safari/537.36",
    "version": null,
    "language": "C.UTF-8"
  }
}