{
  "name": "Nyne",
  "dots": [
    {
      "x": 136.814453125,
      "y": 162.294921875,
      "type": "1"
    },
    {
      "x": 282.814453125,
      "y": 357.294921875,
      "type": "1"
    },
    {
      "x": 193.814453125,
      "y": 298.294921875,
      "type": "1"
    },
    {
      "x": 339.814453125,
      "y": 177.294921875,
      "type": "3"
    },
    {
      "x": 141.814453125,
      "y": 208.294921875,
      "type": "2"
    },
    {
      "x": 184.814453125,
      "y": 238.294921875,
      "type": "2"
    },
    {
      "x": 196.814453125,
      "y": 178.294921875,
      "type": "2"
    },
    {
      "x": 160.814453125,
      "y": 138.294921875,
      "type": "2"
    },
    {
      "x": 127.814453125,
      "y": 143.294921875,
      "type": "2"
    },
    {
      "x": 226.814453125,
      "y": 174.294921875,
      "type": "2"
    },
    {
      "x": 242.814453125,
      "y": 143.294921875,
      "type": "2"
    },
    {
      "x": 275.814453125,
      "y": 152.294921875,
      "type": "2"
    },
    {
      "x": 279.814453125,
      "y": 197.294921875,
      "type": "2"
    },
    {
      "x": 223.814453125,
      "y": 207.294921875,
      "type": "2"
    },
    {
      "x": 260.814453125,
      "y": 276.294921875,
      "type": "2"
    },
    {
      "x": 303.814453125,
      "y": 282.294921875,
      "type": "2"
    },
    {
      "x": 284.814453125,
      "y": 306.294921875,
      "type": "2"
    },
    {
      "x": 243.814453125,
      "y": 294.294921875,
      "type": "2"
    },
    {
      "x": 248.814453125,
      "y": 349.294921875,
      "type": "2"
    },
    {
      "x": 192.814453125,
      "y": 339.294921875,
      "type": "2"
    },
    {
      "x": 167.814453125,
      "y": 312.294921875,
      "type": "2"
    },
    {
      "x": 347.814453125,
      "y": 348.294921875,
      "type": "2"
    },
    {
      "x": 317.814453125,
      "y": 355.294921875,
      "type": "2"
    },
    {
      "x": 341.814453125,
      "y": 309.294921875,
      "type": "2"
    },
    {
      "x": 359.814453125,
      "y": 280.294921875,
      "type": "2"
    },
    {
      "x": 329.814453125,
      "y": 240.294921875,
      "type": "2"
    },
    {
      "x": 374.814453125,
      "y": 240.294921875,
      "type": "2"
    },
    {
      "x": 380.814453125,
      "y": 336.294921875,
      "type": "2"
    },
    {
      "x": 382.814453125,
      "y": 374.294921875,
      "type": "2"
    },
    {
      "x": 343.814453125,
      "y": 377.294921875,
      "type": "2"
    },
    {
      "x": 176.814453125,
      "y": 372.294921875,
      "type": "2"
    },
    {
      "x": 315.814453125,
      "y": 158.544921875,
      "type": "2"
    },
    {
      "x": 154.814453125,
      "y": 285.669921875,
      "type": "2"
    }
  ],
  "ip": "20.0.0.6",
  "serverUTCDate": "2020-10-25T12:52:30.845405",
  "clientDate": "",
  "userAgent": {
    "browser": "Mozilla/5.0 (X11; CrOS x86_64 12871.91.0) AppleWebKit/537.36 (KHTML, like Gecko) Chrome/81.0.4044.127 Safari/537.36",
    "version": null,
    "language": "C.UTF-8"
  }
}